setup.cfg
setup.py
Scotty.egg-info/PKG-INFO
Scotty.egg-info/SOURCES.txt
Scotty.egg-info/dependency_links.txt
Scotty.egg-info/entry_points.txt
Scotty.egg-info/not-zip-safe
Scotty.egg-info/requires.txt
Scotty.egg-info/top_level.txt
scotty/__init__.py
scotty/core.py
scotty/ecs.py
scotty/version.py