Metadata-Version: 1.1
Name: Scotty
Version: 0.1.5
Summary: AWS ECS Container Deployment Tool
Home-page: https://github.com/laco/python-scotty/
Author: László Andrási
Author-email: mail@laszloandrasi.com
License: Apache2.0
Download-URL: https://github.com/laco/python-scotty/tarball/0.1.5
Platform: any
Classifier: Development Status :: 4 - Beta
Classifier: Environment :: Web Environment
Classifier: Intended Audience :: Developers
Classifier: License :: OSI Approved :: BSD License
Classifier: Operating System :: OS Independent
Classifier: Programming Language :: Python
Classifier: Programming Language :: Python :: 3
Classifier: Topic :: Software Development :: Libraries :: Python Modules
